pyzor/__init__.py
pyzor/account.py
pyzor/client.py
pyzor/config.py
pyzor/digest.py
pyzor/forwarder.py
pyzor/message.py
pyzor/server.py
pyzor/engines/__init__.py
pyzor/engines/common.py
pyzor/engines/gdbm_.py
pyzor/engines/mysql.py
pyzor/engines/redis_.py
pyzor/engines/redis_v0.py
pyzor/hacks/__init__.py
pyzor/hacks/py26.py
pyzor/hacks/py3.py
pyzor-1.1.2.data/scripts/pyzor
pyzor-1.1.2.data/scripts/pyzor-migrate
pyzor-1.1.2.data/scripts/pyzord
pyzor-1.1.2.dist-info/COPYING
pyzor-1.1.2.dist-info/METADATA
pyzor-1.1.2.dist-info/WHEEL
pyzor-1.1.2.dist-info/top_level.txt
pyzor-1.1.2.dist-info/RECORD
