Metadata-Version: 2.1
Name: pyzor
Version: 1.1.2
Summary: networked spam-signature detection
Home-page: http://www.pyzor.org/
Author: Frank J. Tobin
Author-email: ftobin@neverending.org
License: GPL
Keywords: spam
Platform: POSIX
Classifier: Operating System :: POSIX
Classifier: Operating System :: Microsoft :: Windows
Classifier: Environment :: Console
Classifier: Environment :: No Input/Output (Daemon)
Classifier: Programming Language :: Python
Classifier: Programming Language :: Python :: 2.6
Classifier: Programming Language :: Python :: 3
Classifier: Intended Audience :: System Administrators
Classifier: Topic :: Communications :: Email
Classifier: Topic :: Communications :: Email :: Filters
Classifier: Development Status :: 5 - Production/Stable
Classifier: License :: OSI Approved :: GNU General Public License v2 (GPLv2)
License-File: COPYING
